[
  {
    "type": "start",
    "details": {}
  },
  {
    "type": "deal",
    "details": {
      "deck": [
        {
          "rank": "9",
          "suit": "♠️"
        },
        {
          "rank": "8",
          "suit": "♣️"
        },
        {
          "rank": "3",
          "suit": "♥️"
        },
        {
          "rank": "A",
          "suit": "♥️"
        },
        {
          "rank": "6",
          "suit": "♣️"
        },
        {
          "rank": "6",
          "suit": "♠️"
        },
        {
          "rank": "5",
          "suit": "♦️"
        },
        {
          "rank": "7",
          "suit": "♦️"
        },
        {
          "rank": "10",
          "suit": "♠️"
        },
        {
          "rank": "9",
          "suit": "♦️"
        },
        {
          "rank": "8",
          "suit": "♥️"
        },
        {
          "rank": "10",
          "suit": "♥️"
        },
        {
          "rank": "4",
          "suit": "♣️"
        },
        {
          "rank": "7",
          "suit": "♣️"
        },
        {
          "rank": "Q",
          "suit": "♦️"
        },
        {
          "rank": "8",
          "suit": "♠️"
        },
        {
          "rank": "K",
          "suit": "♠️"
        },
        {
          "rank": "K",
          "suit": "♥️"
        },
        {
          "rank": "5",
          "suit": "♠️"
        },
        {
          "rank": "J",
          "suit": "♠️"
        },
        {
          "rank": "2",
          "suit": "♠️"
        },
        {
          "rank": "7",
          "suit": "♥️"
        },
        {
          "rank": "A",
          "suit": "♠️"
        },
        {
          "rank": "A",
          "suit": "♦️"
        },
        {
          "rank": "3",
          "suit": "♣️"
        },
        {
          "rank": "3",
          "suit": "♦️"
        },
        {
          "rank": "9",
          "suit": "♣️"
        },
        {
          "rank": "4",
          "suit": "♦️"
        },
        {
          "rank": "J",
          "suit": "♦️"
        },
        {
          "rank": "2",
          "suit": "♣️"
        },
        {
          "rank": "J",
          "suit": "♥️"
        },
        {
          "rank": "5",
          "suit": "♥️"
        },
        {
          "rank": "Q",
          "suit": "♥️"
        },
        {
          "rank": "Q",
          "suit": "♠️"
        },
        {
          "rank": "3",
          "suit": "♠️"
        },
        {
          "rank": "9",
          "suit": "♥️"
        },
        {
          "rank": "6",
          "suit": "♥️"
        },
        {
          "rank": "Q",
          "suit": "♣️"
        },
        {
          "rank": "5",
          "suit": "♣️"
        },
        {
          "rank": "10",
          "suit": "♣️"
        },
        {
          "rank": "10",
          "suit": "♦️"
        },
        {
          "rank": "8",
          "suit": "♦️"
        },
        {
          "rank": "6",
          "suit": "♦️"
        },
        {
          "rank": "K",
          "suit": "♦️"
        },
        {
          "rank": "K",
          "suit": "♣️"
        },
        {
          "rank": "2",
          "suit": "♥️"
        },
        {
          "rank": "A",
          "suit": "♣️"
        }
      ],
      "hands": [
        [
          {
            "rank": "7",
            "suit": "♠️"
          }
        ],
        [
          {
            "rank": "4",
            "suit": "♥️"
          }
        ],
        [
          {
            "rank": "2",
            "suit": "♦️"
          }
        ],
        [
          {
            "rank": "4",
            "suit": "♠️"
          }
        ]
      ],
      "trump": {
        "rank": "J",
        "suit": "♣️"
      },
      "round": 0
    }
  },
  {
    "seat": 0,
    "type": "bid",
    "details": {
      "bid": 1
    }
  },
  {
    "seat": 1,
    "type": "bid",
    "details": {
      "bid": 1
    }
  },
  {
    "seat": 2,
    "type": "bid",
    "details": {
      "bid": 1
    }
  },
  {
    "seat": 3,
    "type": "bid",
    "details": {
      "bid": 1
    }
  },
  {
    "seat": 0,
    "type": "play",
    "details": {
      "card": {
        "rank": "7",
        "suit": "♠️"
      }
    }
  },
  {
    "seat": 0,
    "type": "commit"
  },
  {
    "seat": 1,
    "type": "play",
    "details": {
      "card": {
        "rank": "4",
        "suit": "♥️"
      }
    }
  },
  {
    "seat": 1,
    "type": "commit"
  },
  {
    "seat": 2,
    "type": "play",
    "details": {
      "card": {
        "rank": "2",
        "suit": "♦️"
      }
    }
  },
  {
    "seat": 2,
    "type": "commit"
  },
  {
    "seat": 3,
    "type": "play",
    "details": {
      "card": {
        "rank": "4",
        "suit": "♠️"
      }
    }
  },
  {
    "type": "award",
    "details": {
      "winner": 0,
      "trick": [
        {
          "rank": "7",
          "suit": "♠️"
        },
        {
          "rank": "4",
          "suit": "♥️"
        },
        {
          "rank": "2",
          "suit": "♦️"
        },
        {
          "rank": "4",
          "suit": "♠️"
        }
      ]
    }
  },
  {
    "seat": 3,
    "type": "commit"
  },
  {
    "seat": null,
    "type": "scoring",
    "details": {
      "scoring": [
        {
          "bid": 1,
          "tricks": 1,
          "points": 11
        },
        {
          "bid": 1,
          "tricks": 0,
          "points": 0
        },
        {
          "bid": 1,
          "tricks": 0,
          "points": 0
        },
        {
          "bid": 1,
          "tricks": 0,
          "points": 0
        }
      ]
    }
  },
  {
    "type": "deal",
    "details": {
      "deck": [
        {
          "rank": "2",
          "suit": "♣️"
        },
        {
          "rank": "10",
          "suit": "♦️"
        },
        {
          "rank": "Q",
          "suit": "♦️"
        },
        {
          "rank": "J",
          "suit": "♥️"
        },
        {
          "rank": "9",
          "suit": "♣️"
        },
        {
          "rank": "7",
          "suit": "♥️"
        },
        {
          "rank": "7",
          "suit": "♣️"
        },
        {
          "rank": "10",
          "suit": "♠️"
        },
        {
          "rank": "K",
          "suit": "♣️"
        },
        {
          "rank": "J",
          "suit": "♣️"
        },
        {
          "rank": "6",
          "suit": "♥️"
        },
        {
          "rank": "K",
          "suit": "♥️"
        },
        {
          "rank": "3",
          "suit": "♥️"
        },
        {
          "rank": "A",
          "suit": "♣️"
        },
        {
          "rank": "4",
          "suit": "♥️"
        },
        {
          "rank": "7",
          "suit": "♦️"
        },
        {
          "rank": "2",
          "suit": "♦️"
        },
        {
          "rank": "A",
          "suit": "♦️"
        },
        {
          "rank": "8",
          "suit": "♣️"
        },
        {
          "rank": "9",
          "suit": "♦️"
        },
        {
          "rank": "5",
          "suit": "♣️"
        },
        {
          "rank": "2",
          "suit": "♠️"
        },
        {
          "rank": "9",
          "suit": "♠️"
        },
        {
          "rank": "3",
          "suit": "♦️"
        },
        {
          "rank": "3",
          "suit": "♣️"
        },
        {
          "rank": "A",
          "suit": "♠️"
        },
        {
          "rank": "4",
          "suit": "♠️"
        },
        {
          "rank": "6",
          "suit": "♣️"
        },
        {
          "rank": "4",
          "suit": "♣️"
        },
        {
          "rank": "K",
          "suit": "♦️"
        },
        {
          "rank": "5",
          "suit": "♥️"
        },
        {
          "rank": "6",
          "suit": "♦️"
        },
        {
          "rank": "9",
          "suit": "♥️"
        },
        {
          "rank": "8",
          "suit": "♥️"
        },
        {
          "rank": "2",
          "suit": "♥️"
        },
        {
          "rank": "5",
          "suit": "♠️"
        },
        {
          "rank": "4",
          "suit": "♦️"
        },
        {
          "rank": "7",
          "suit": "♠️"
        },
        {
          "rank": "10",
          "suit": "♣️"
        },
        {
          "rank": "Q",
          "suit": "♥️"
        },
        {
          "rank": "K",
          "suit": "♠️"
        },
        {
          "rank": "Q",
          "suit": "♣️"
        },
        {
          "rank": "J",
          "suit": "♦️"
        }
      ],
      "hands": [
        [
          {
            "rank": "5",
            "suit": "♦️"
          },
          {
            "rank": "6",
            "suit": "♠️"
          }
        ],
        [
          {
            "rank": "J",
            "suit": "♠️"
          },
          {
            "rank": "Q",
            "suit": "♠️"
          }
        ],
        [
          {
            "rank": "A",
            "suit": "♥️"
          },
          {
            "rank": "10",
            "suit": "♥️"
          }
        ],
        [
          {
            "rank": "8",
            "suit": "♠️"
          },
          {
            "rank": "8",
            "suit": "♦️"
          }
        ]
      ],
      "trump": {
        "rank": "3",
        "suit": "♠️"
      },
      "round": 1
    }
  },
  {
    "seat": 0,
    "type": "bid",
    "details": {
      "bid": 1
    }
  },
  {
    "seat": 1,
    "type": "bid",
    "details": {
      "bid": 1
    }
  },
  {
    "seat": 2,
    "type": "bid",
    "details": {
      "bid": 1
    }
  },
  {
    "seat": 3,
    "type": "bid",
    "details": {
      "bid": 1
    }
  },
  {
    "seat": 1,
    "type": "play",
    "details": {
      "card": {
        "rank": "Q",
        "suit": "♠️"
      }
    }
  },
  {
    "seat": 1,
    "type": "commit",
    "details": {
      "card": {
        "rank": "J",
        "suit": "♠️"
      }
    }
  },
  {
    "seat": 2,
    "type": "play",
    "details": {
      "card": {
        "rank": "10",
        "suit": "♥️"
      }
    }
  },
  {
    "seat": 2,
    "type": "commit",
    "details": {
      "card": {
        "rank": "A",
        "suit": "♥️"
      }
    }
  },
  {
    "seat": 3,
    "type": "play",
    "details": {
      "card": {
        "rank": "8",
        "suit": "♠️"
      }
    }
  },
  {
    "seat": 3,
    "type": "commit",
    "details": {
      "card": {
        "rank": "8",
        "suit": "♦️"
      }
    }
  },
  {
    "seat": 0,
    "type": "play",
    "details": {
      "card": {
        "rank": "6",
        "suit": "♠️"
      }
    }
  },
  {
    "type": "award",
    "details": {
      "winner": 0,
      "trick": [
        {
          "rank": "Q",
          "suit": "♠️"
        },
        {
          "rank": "10",
          "suit": "♥️"
        },
        {
          "rank": "8",
          "suit": "♠️"
        },
        {
          "rank": "6",
          "suit": "♠️"
        }
      ]
    }
  },
  {
    "seat": 0,
    "type": "commit",
    "details": {
      "card": {
        "rank": "5",
        "suit": "♦️"
      }
    }
  },
  {
    "seat": 1,
    "type": "play",
    "details": {
      "card": {
        "rank": "J",
        "suit": "♠️"
      }
    }
  },
  {
    "seat": 1,
    "type": "commit"
  },
  {
    "seat": 2,
    "type": "play",
    "details": {
      "card": {
        "rank": "A",
        "suit": "♥️"
      }
    }
  },
  {
    "seat": 2,
    "type": "commit"
  },
  {
    "seat": 3,
    "type": "play",
    "details": {
      "card": {
        "rank": "8",
        "suit": "♦️"
      }
    }
  },
  {
    "seat": 3,
    "type": "commit"
  },
  {
    "seat": 0,
    "type": "play",
    "details": {
      "card": {
        "rank": "5",
        "suit": "♦️"
      }
    }
  },
  {
    "type": "award",
    "details": {
      "winner": 1,
      "trick": [
        {
          "rank": "5",
          "suit": "♦️"
        },
        {
          "rank": "J",
          "suit": "♠️"
        },
        {
          "rank": "A",
          "suit": "♥️"
        },
        {
          "rank": "8",
          "suit": "♦️"
        }
      ]
    }
  },
  {
    "seat": 0,
    "type": "commit"
  },
  {
    "seat": null,
    "type": "scoring",
    "details": {
      "scoring": [
        {
          "bid": 1,
          "tricks": 1,
          "points": 11
        },
        {
          "bid": 1,
          "tricks": 1,
          "points": 11
        },
        {
          "bid": 1,
          "tricks": 0,
          "points": 0
        },
        {
          "bid": 1,
          "tricks": 0,
          "points": 0
        }
      ]
    }
  },
  {
    "type": "deal",
    "details": {
      "deck": [
        {
          "rank": "2",
          "suit": "♠️"
        },
        {
          "rank": "3",
          "suit": "♥️"
        },
        {
          "rank": "6",
          "suit": "♦️"
        },
        {
          "rank": "9",
          "suit": "♦️"
        },
        {
          "rank": "5",
          "suit": "♥️"
        },
        {
          "rank": "K",
          "suit": "♣️"
        },
        {
          "rank": "Q",
          "suit": "♥️"
        },
        {
          "rank": "Q",
          "suit": "♠️"
        },
        {
          "rank": "8",
          "suit": "♥️"
        },
        {
          "rank": "8",
          "suit": "♦️"
        },
        {
          "rank": "10",
          "suit": "♠️"
        },
        {
          "rank": "9",
          "suit": "♥️"
        },
        {
          "rank": "2",
          "suit": "♦️"
        },
        {
          "rank": "J",
          "suit": "♥️"
        },
        {
          "rank": "Q",
          "suit": "♣️"
        },
        {
          "rank": "7",
          "suit": "♦️"
        },
        {
          "rank": "7",
          "suit": "♠️"
        },
        {
          "rank": "10",
          "suit": "♣️"
        },
        {
          "rank": "A",
          "suit": "♣️"
        },
        {
          "rank": "8",
          "suit": "♠️"
        },
        {
          "rank": "8",
          "suit": "♣️"
        },
        {
          "rank": "3",
          "suit": "♣️"
        },
        {
          "rank": "4",
          "suit": "♥️"
        },
        {
          "rank": "5",
          "suit": "♣️"
        },
        {
          "rank": "4",
          "suit": "♠️"
        },
        {
          "rank": "A",
          "suit": "♥️"
        },
        {
          "rank": "2",
          "suit": "♥️"
        },
        {
          "rank": "A",
          "suit": "♠️"
        },
        {
          "rank": "6",
          "suit": "♠️"
        },
        {
          "rank": "J",
          "suit": "♦️"
        },
        {
          "rank": "10",
          "suit": "♦️"
        },
        {
          "rank": "5",
          "suit": "♦️"
        },
        {
          "rank": "J",
          "suit": "♠️"
        },
        {
          "rank": "6",
          "suit": "♥️"
        },
        {
          "rank": "10",
          "suit": "♥️"
        },
        {
          "rank": "Q",
          "suit": "♦️"
        },
        {
          "rank": "5",
          "suit": "♠️"
        },
        {
          "rank": "2",
          "suit": "♣️"
        },
        {
          "rank": "J",
          "suit": "♣️"
        },
        {
          "rank": "7",
          "suit": "♥️"
        },
        {
          "rank": "4",
          "suit": "♦️"
        },
        {
          "rank": "3",
          "suit": "♠️"
        },
        {
          "rank": "A",
          "suit": "♦️"
        },
        {
          "rank": "7",
          "suit": "♣️"
        },
        {
          "rank": "9",
          "suit": "♣️"
        },
        {
          "rank": "6",
          "suit": "♣️"
        },
        {
          "rank": "K",
          "suit": "♦️"
        }
      ],
      "hands": [
        [
          {
            "rank": "9",
            "suit": "♠️"
          }
        ],
        [
          {
            "rank": "3",
            "suit": "♦️"
          }
        ],
        [
          {
            "rank": "K",
            "suit": "♥️"
          }
        ],
        [
          {
            "rank": "K",
            "suit": "♠️"
          }
        ]
      ],
      "trump": {
        "rank": "4",
        "suit": "♣️"
      },
      "round": 2
    }
  },
  {
    "seat": 0,
    "type": "bid",
    "details": {
      "bid": 1
    }
  },
  {
    "seat": 1,
    "type": "bid",
    "details": {
      "bid": 1
    }
  },
  {
    "seat": 2,
    "type": "bid",
    "details": {
      "bid": 1
    }
  },
  {
    "seat": 3,
    "type": "bid",
    "details": {
      "bid": 1
    }
  },
  {
    "seat": 2,
    "type": "play",
    "details": {
      "card": {
        "rank": "K",
        "suit": "♥️"
      }
    }
  },
  {
    "seat": 2,
    "type": "commit"
  },
  {
    "seat": 3,
    "type": "play",
    "details": {
      "card": {
        "rank": "K",
        "suit": "♠️"
      }
    }
  },
  {
    "seat": 3,
    "type": "commit"
  },
  {
    "seat": 0,
    "type": "play",
    "details": {
      "card": {
        "rank": "9",
        "suit": "♠️"
      }
    }
  },
  {
    "seat": 0,
    "type": "commit"
  },
  {
    "seat": 1,
    "type": "play",
    "details": {
      "card": {
        "rank": "3",
        "suit": "♦️"
      }
    }
  },
  {
    "type": "award",
    "details": {
      "winner": 0,
      "trick": [
        {
          "rank": "K",
          "suit": "♥️"
        },
        {
          "rank": "K",
          "suit": "♠️"
        },
        {
          "rank": "9",
          "suit": "♠️"
        },
        {
          "rank": "3",
          "suit": "♦️"
        }
      ]
    }
  },
  {
    "seat": 1,
    "type": "commit"
  },
  {
    "seat": null,
    "type": "scoring",
    "details": {
      "scoring": [
        {
          "bid": 1,
          "tricks": 1,
          "points": 11
        },
        {
          "bid": 1,
          "tricks": 0,
          "points": 0
        },
        {
          "bid": 1,
          "tricks": 0,
          "points": 0
        },
        {
          "bid": 1,
          "tricks": 0,
          "points": 0
        }
      ]
    }
  },
  {
    "type": "finish",
    "details": {
      "ranked": [
        {
          "seat": 0,
          "points": 33,
          "place": 0,
          "tie": false
        },
        {
          "seat": 1,
          "points": 11,
          "place": 1,
          "tie": false
        },
        {
          "seat": 2,
          "points": 0,
          "place": 2,
          "tie": true
        },
        {
          "seat": 3,
          "points": 0,
          "place": 2,
          "tie": true
        }
      ]
    }
  }
]
